ba/__init__.py
ba-0.0.6.dist-info/licenses/LICENSE
ba-0.0.6.dist-info/METADATA
ba-0.0.6.dist-info/WHEEL
ba-0.0.6.dist-info/top_level.txt
ba-0.0.6.dist-info/RECORD
