Metadata-Version: 2.4
Name: ba
Version: 0.0.6
Summary: Making diagrams easily.
Home-page: https://github.com/t-c-w/ba
Author: Thor Whalen
License: apache-2.0
Platform: any
License-File: LICENSE
Dynamic: license-file
